decalmlutils/__init__.py
decalmlutils/debug_info.py
decalmlutils/logging_utils.py
decalmlutils/misc.py
decalmlutils/testing.py
decalmlutils/text.py
decalmlutils/distributed/__init__.py
decalmlutils/distributed/ray_utils.py
decalmlutils/ds/__init__.py
decalmlutils/ds/dataframes.py
decalmlutils/ds/np_memmap.py
decalmlutils/ds/tensors.py
decalmlutils/ds/training.py
decalmlutils/geo/__init__.py
decalmlutils/geo/geojson.py
decalmlutils/geo/geom.py
decalmlutils/git_/__init__.py
decalmlutils/git_/git_.py
decalmlutils/io/__init__.py
decalmlutils/io/context.py
decalmlutils/io/sort.py
decalmlutils/io/disk/__init__.py
decalmlutils/io/disk/compressed_writer.py
decalmlutils/io/disk/img.py
decalmlutils/io/disk/json.py
decalmlutils/io/disk/misc.py
decalmlutils/io/disk/parquet.py
decalmlutils/io/disk/yaml.py
decalmlutils/jira_/__init__.py
decalmlutils/jira_/jira_.py
decalmlutils/metrics/__init__.py
decalmlutils/metrics/misc.py
decalmlutils/metrics/prg.py
decalmlutils/metrics/rankme.py
decalmlutils/mflow/__init__.py
decalmlutils/mflow/artifacts.py
decalmlutils/mflow/cloudwatch_logs.py
decalmlutils/mflow/decorators.py
decalmlutils/mflow/deps.py
decalmlutils/mflow/flows.py
decalmlutils/mflow/lineage.py
decalmlutils/mflow/runs.py
decalmlutils/mflow/tasks.py
decalmlutils/mflow/workflows.py
decalmlutils/profiling/__init__.py
decalmlutils/profiling/profiling.py
decalmlutils/slack/__init__.py
decalmlutils/slack/slack.py
decalmlutils/viz/__init__.py
decalmlutils/viz/plotting.py
decalmlutils/web/__init__.py
decalmlutils/web/web.py
decalmlutils-0.0.13.dist-info/LICENSE
decalmlutils-0.0.13.dist-info/METADATA
decalmlutils-0.0.13.dist-info/WHEEL
decalmlutils-0.0.13.dist-info/top_level.txt
decalmlutils-0.0.13.dist-info/RECORD
